github_latest/__init__.py
github_latest/__main__.py
github_latest/args.py
github_latest/cli.py
github_latest/resolver.py
github_latest-0.5.2.dist-info/AUTHORS.rst
github_latest-0.5.2.dist-info/LICENSE
github_latest-0.5.2.dist-info/METADATA
github_latest-0.5.2.dist-info/WHEEL
github_latest-0.5.2.dist-info/entry_points.txt
github_latest-0.5.2.dist-info/top_level.txt
github_latest-0.5.2.dist-info/RECORD
