Metadata-Version: 2.1
Name: github-latest
Version: 0.5.2
Summary: An example package. Generated with cookiecutter-pylibrary.
Home-page: https://github.com/TaylorMonacelli/python-github_latest
Author: Taylor Monacelli
Author-email: taylormonacelli@gmail.com
License: BSD-2-Clause
Project-URL: Documentation, https://python-github_latest.readthedocs.io/
Project-URL: Changelog, https://python-github_latest.readthedocs.io/en/latest/changelog.html
Project-URL: Issue Tracker, https://github.com/TaylorMonacelli/python-github_latest/issues
Classifier: Development Status :: 5 - Production/Stable
Classifier: Intended Audience :: Developers
Classifier: License :: OSI Approved :: BSD License
Classifier: Operating System :: Unix
Classifier: Operating System :: POSIX
Classifier: Operating System :: Microsoft :: Windows
Classifier: Programming Language :: Python
Classifier: Programming Language :: Python :: 3
Classifier: Programming Language :: Python :: 3 :: Only
Classifier: Programming Language :: Python :: 3.7
Classifier: Programming Language :: Python :: 3.8
Classifier: Programming Language :: Python :: 3.9
Classifier: Programming Language :: Python :: Implementation :: CPython
Classifier: Programming Language :: Python :: Implementation :: PyPy
Classifier: Topic :: Utilities
Requires-Python: >=3.6
License-File: LICENSE
License-File: AUTHORS.rst
Requires-Dist: requests
Requires-Dist: monacelli-pylog-prefs
